Metadata-Version: 2.2
Name: control-systems-toolbox
Version: 0.0.1
Summary: A control systems design and simulation toolbox
Home-page: 
Author: Seth Reed
Author-email: seth.reed01@gmail.com
License: MIT
Keywords: control
Classifier: Development Status :: 1 - Planning
Classifier: Intended Audience :: Developers
Classifier: Operating System :: Microsoft :: Windows :: Windows 11
Classifier: License :: OSI Approved :: MIT License
Classifier: Programming Language :: Python :: 3
License-File: LICENSE
Dynamic: author
Dynamic: author-email
Dynamic: classifier
Dynamic: description
Dynamic: description-content-type
Dynamic: keywords
Dynamic: license
Dynamic: summary
